libname/__init__.py
libname/chatterpyv1.py
chatterpyv1-0.1.0.dist-info/LICENSE
chatterpyv1-0.1.0.dist-info/METADATA
chatterpyv1-0.1.0.dist-info/WHEEL
chatterpyv1-0.1.0.dist-info/top_level.txt
chatterpyv1-0.1.0.dist-info/RECORD
